ps_eor/__init__.py
ps_eor/config/default_ml_gpr_settings.toml
ps_eor/convert_sage_solutions.py
ps_eor/convert_sage_zsol.py
ps_eor/datacube.py
ps_eor/fgfit.py
ps_eor/fitutil.py
ps_eor/flagger.py
ps_eor/instru/aartfaac_a12_hba_statpos.data
ps_eor/instru/aartfaac_a12_lba_statpos.data
ps_eor/instru/lofar_statpos.data
ps_eor/instru/mwa_rev1_lonlat.data
ps_eor/instru/mwa_rev1_statpos.data
ps_eor/instru/nenufar80_statpos.data
ps_eor/instru/nenufar_full_statpos.data
ps_eor/instru/nenufar_full_statpos_lonlat.data
ps_eor/instru/ovro-lwa_enu_statpos.data
ps_eor/instru/ska1_low_aa2_enu_statpos.data
ps_eor/instru/ska1_low_aastar_enu_statpos.data
ps_eor/instru/ska1_low_enu_statpos.data
ps_eor/ml_gpr.py
ps_eor/obssimu.py
ps_eor/pscart.py
ps_eor/pspec.py
ps_eor/pssph.py
ps_eor/psutil.py
ps_eor/run_powerspectra.py
ps_eor/simu.py
ps_eor/sphcube.py
ps_eor/sphutil.py
ps_eor/tests/test_datacube.py
ps_eor/tools/__init__.py
ps_eor/tools/pstool.py
ps_eor-0.34.1.dist-info/LICENSE
ps_eor-0.34.1.dist-info/METADATA
ps_eor-0.34.1.dist-info/WHEEL
ps_eor-0.34.1.dist-info/entry_points.txt
ps_eor-0.34.1.dist-info/RECORD
