Metadata-Version: 2.3
Name: ps_eor
Version: 0.34.1
Summary: Power Spectra generation for 21-cm experiments and Foreground modeling/removal
License: GPL-3.0-or-later
Author: Florent Mertens
Author-email: flomertens@gmail.com
Requires-Python: >=3.10,<4.0
Classifier: License :: OSI Approved :: GNU General Public License v3 or later (GPLv3+)
Classifier: Programming Language :: Python :: 3
Classifier: Programming Language :: Python :: 3.10
Classifier: Programming Language :: Python :: 3.11
Classifier: Programming Language :: Python :: 3.12
Classifier: Programming Language :: Python :: 3.13
Provides-Extra: ml-gpr
Requires-Dist: GPy (>=1.10,!=1.12.0) ; extra == "ml-gpr"
Requires-Dist: astropy (>=6.0)
Requires-Dist: click (>=8.0)
Requires-Dist: configparser (>=6.0)
Requires-Dist: corner (>=2.2) ; extra == "ml-gpr"
Requires-Dist: dynesty (>=2.0) ; extra == "ml-gpr"
Requires-Dist: emcee (>=3.1) ; extra == "ml-gpr"
Requires-Dist: fast-histogram (>=0.11)
Requires-Dist: h5py (>=3.10)
Requires-Dist: healpy (>=1.16)
Requires-Dist: joblib (>=1.3)
Requires-Dist: libpipe (>=0.1.5) ; extra == "ml-gpr"
Requires-Dist: matplotlib (>=3.8)
Requires-Dist: numpy (>=1.20)
Requires-Dist: pandas (>=2.0) ; extra == "ml-gpr"
Requires-Dist: pyfftw (>=0.13)
Requires-Dist: reproject (>=0.14)
Requires-Dist: scikit-learn (>=1.3)
Requires-Dist: scipy (>=1.10)
Requires-Dist: tables (>=3.9)
Requires-Dist: torch (>=2.0) ; extra == "ml-gpr"
Requires-Dist: ultranest (>=3.0) ; extra == "ml-gpr"
